NextPClogic.v
`timescale 1ns / 1ps

module NextPClogic(
    output reg [63:0] NextPC,
    input  [63:0] CurrentPC,
    input  [63:0] SignExtImm64,
    input         Branch,
    input         ALUZero,
    input         Uncondbranch
);

    always @(*) begin
        if (Uncondbranch) begin
            // Unconditional branch: PC = CurrentPC + SignExtImm64
            NextPC = CurrentPC + SignExtImm64;
        end
        else if (Branch && ALUZero) begin
            // Conditional branch taken (CBZ and ALU result is zero): PC = CurrentPC + SignExtImm64
            NextPC = CurrentPC + SignExtImm64;
        end
        else begin
            // No branch or branch not taken: PC = CurrentPC + 4
            NextPC = CurrentPC + 64'd4;
        end
    end

endmodule

DataMemory.v
`timescale 1ns / 1ps

`define SIZE 1024

module DataMemory(ReadData , Address , WriteData , MemoryRead , MemoryWrite , Clock);
   input [63:0]      WriteData;
   input [63:0]      Address;
   input             Clock, MemoryRead, MemoryWrite;
   output reg [63:0] ReadData;

   reg [7:0] 	     memBank [`SIZE-1:0];


   // This task is used to write arbitrary data to the Data Memory by
   // the intialization block.
   task initset;
      input [63:0] addr;
      input [63:0] data;
      begin
	 memBank[addr] =  data[63:56] ; // Big-endian for the win...
	 memBank[addr+1] =  data[55:48];
	 memBank[addr+2] =  data[47:40];
	 memBank[addr+3] =  data[39:32];
	 memBank[addr+4] =  data[31:24];
	 memBank[addr+5] =  data[23:16];
	 memBank[addr+6] =  data[15:8];
	 memBank[addr+7] =  data[7:0];
      end
   endtask


   initial
     begin
        // preseting some data in the data memory used by test #1

        // Address 0x0 gets 0x1
        initset( 64'h0,  64'h1);  //Counter variable
        initset( 64'h8,  64'ha);  //Part of mask
        initset( 64'h10, 64'h5);  //Other part of mask
        initset( 64'h18, 64'h0ffbea7deadbeeff); //big constant
        initset( 64'h20, 64'h0); //clearing space

        // Add any data you need for your tests here.

     end

   // This always block reads the data memory and places a double word
   // on the ReadData bus.
   // Changed to combinational (asynchronous) read for single-cycle processor
   always @(*)
     begin
        if(MemoryRead)
          begin
             ReadData[63:56] =  memBank[Address];
             ReadData[55:48] =  memBank[Address+1];
             ReadData[47:40] =  memBank[Address+2];
             ReadData[39:32] =  memBank[Address+3];
             ReadData[31:24] =  memBank[Address+4];
             ReadData[23:16] =  memBank[Address+5];
             ReadData[15:8] =  memBank[Address+6];
             ReadData[7:0] =  memBank[Address+7];
          end
        else
          begin
             ReadData = 64'b0;
          end
     end

   // This always block takes data from the WriteData bus and writes
   // it into the DataMemory.
   always @(posedge Clock)
     begin
        if(MemoryWrite)
          begin
             memBank[Address] <= #3 WriteData[63:56] ;
             memBank[Address+1] <= #3 WriteData[55:48];
             memBank[Address+2] <= #3 WriteData[47:40];
             memBank[Address+3] <= #3 WriteData[39:32];
             memBank[Address+4] <= #3 WriteData[31:24];
             memBank[Address+5] <= #3 WriteData[23:16];
             memBank[Address+6] <= #3 WriteData[15:8];
             memBank[Address+7] <= #3 WriteData[7:0];
             // Could be useful for debugging:
             // $display("Writing Address:%h Data:%h",Address, WriteData);
          end
     end
endmodule

ALU.v
`timescale 1ns / 1ps

`define AND   4'b0000
`define OR    4'b0001
`define ADD   4'b0010
`define SUB   4'b0110
`define PassB 4'b0111

module ALU(
    output reg [63:0] BusW,
    input      [63:0] BusA,
    input      [63:0] BusB,
    input      [3:0]  ALUCtrl,
    output            Zero
);

    always @(*) begin
        case (ALUCtrl)
            `AND: begin
                BusW = BusA & BusB;
            end
            
            `OR: begin
                BusW = BusA | BusB;
            end
            
            `ADD: begin
                BusW = BusA + BusB;
            end
            
            `SUB: begin
                BusW = BusA - BusB;
            end
            
            `PassB: begin
                BusW = BusB;
            end
            
            default: begin
                BusW = 64'b0;
            end
        endcase
    end
    
    // Zero flag is set when BusW is all zeros
    assign Zero = (BusW == 64'b0);

endmodule

SignExtender.v
`timescale 1ns / 1ps

`define Itype   2'b00
`define Dtype   2'b01
`define CBtype  2'b10
`define Btype   2'b11

module SignExtender(
    output reg [63:0] SignExOut,
    input      [25:0] Instruction,
    input      [1:0]  SignOp
);

    always @(*) begin
        case (SignOp)
            `Itype: begin
                // I-type: 12-bit immediate [21:10], zero extend
                SignExOut = {52'b0, Instruction[21:10]};
            end
            
            `Dtype: begin
                // D-type: 9-bit immediate [20:12], sign extend
                SignExOut = {{55{Instruction[20]}}, Instruction[20:12]};
            end
            
            `CBtype: begin
                // CB-type: 19-bit immediate [23:5], sign extend, shift left by 2
                SignExOut = {{43{Instruction[23]}}, Instruction[23:5], 2'b00};
            end
            
            `Btype: begin
                // B-type: 26-bit immediate [25:0], sign extend, shift left by 2
                SignExOut = {{36{Instruction[25]}}, Instruction[25:0], 2'b00};
            end
            
            default: begin
                SignExOut = 64'b0;
            end
        endcase
    end

endmodule

RegisterFile.v
`timescale 1ns / 1ps

// 32 registers x0..x31, 64-bit wide. x31 is XZR (always 0; writes ignored).
module RegisterFile(
    output wire [63:0] BusA, 
    output wire [63:0] BusB,
    input  wire [63:0] BusW,
    input  wire [4:0]  RA, 
    input  wire [4:0]  RB, 
    input  wire [4:0]  RW,
    input  wire        RegWr,
    input  wire        Clk
);

  // Storage: 32 registers, each 64 bits
  reg [63:0] rf [31:0];

  // Combinational read stage
  reg [63:0] a_next;
  reg [63:0] b_next;

  // Synchronous write (non-blocking). Ignore writes to x31.
  always @(posedge Clk) begin
    if (RegWr && (RW != 5'd31)) begin
      rf[RW] <= BusW;
    end
    // Optionally, keep XZR pinned to zero in storage as well:
    // rf[5'd31] <= 64'b0;
  end

  // Combinational reads (blocking). XZR reads as zero.
  // Includes same-cycle bypass (except to/from x31).
  always @* begin
    a_next = (RA == 5'd31) ? 64'b0 : rf[RA];
    b_next = (RB == 5'd31) ? 64'b0 : rf[RB];

    // Write-through bypass: if writing to same register being read this cycle
    if (RegWr && (RW == RA) && (RW != 5'd31)) a_next = BusW;
    if (RegWr && (RW == RB) && (RW != 5'd31)) b_next = BusW;
  end

  // Required #3 delay on outputs (simulation only; synthesizers ignore delays)
  assign #3 BusA = a_next;
  assign #3 BusB = b_next;

endmodule



// https://chatgpt.com/g/g-p-68fa84289bfc81918d42fdf621b4ce84-will/c/69027e05-f9cc-8322-9263-5ef860e64ef2

SingleCycleControl.v
`timescale 1ns / 1ps

`define OPCODE_ANDREG 11'b10001010000  // Fixed: was 10001011000
`define OPCODE_ORRREG 11'b10101010000
`define OPCODE_ADDREG 11'b10001011000
`define OPCODE_SUBREG 11'b11001011000
`define OPCODE_ADDIMM 11'b1001000100?
`define OPCODE_SUBIMM 11'b1101000100?
`define OPCODE_MOVZ   11'b110100101??
`define OPCODE_B      11'b000101?????
`define OPCODE_CBZ    11'b10110100???
`define OPCODE_LDUR   11'b11111000010
`define OPCODE_STUR   11'b11111000000

module SC_Control(
    output reg       Reg2Loc,
    output reg       ALUSrc,
    output reg       MemtoReg,
    output reg       RegWrite,
    output reg       MemRead,
    output reg       MemWrite,
    output reg       Branch,
    output reg       Uncondbranch,
    output reg [3:0] ALUOp,
    output reg [1:0] SignOp,
    input  [10:0]    opcode
);

    always @(*) begin
        // Default values (all zeros for undefined opcodes)
        Reg2Loc = 1'b0;
        ALUSrc = 1'b0;
        MemtoReg = 1'b0;
        RegWrite = 1'b0;
        MemRead = 1'b0;
        MemWrite = 1'b0;
        Branch = 1'b0;
        Uncondbranch = 1'b0;
        ALUOp = 4'b0000;
        SignOp = 2'b00;

        casez(opcode)
            // R-format instructions (register operations)
            `OPCODE_ADDREG: begin
                Reg2Loc = 1'b0;
                ALUSrc = 1'b0;
                MemtoReg = 1'b0;
                RegWrite = 1'b1;
                MemRead = 1'b0;
                MemWrite = 1'b0;
                Branch = 1'b0;
                Uncondbranch = 1'b0;
                ALUOp = 4'b0010;  // ADD
                SignOp = 2'b00;
            end

            `OPCODE_SUBREG: begin
                Reg2Loc = 1'b0;
                ALUSrc = 1'b0;
                MemtoReg = 1'b0;
                RegWrite = 1'b1;
                MemRead = 1'b0;
                MemWrite = 1'b0;
                Branch = 1'b0;
                Uncondbranch = 1'b0;
                ALUOp = 4'b0110;  // SUB
                SignOp = 2'b00;
            end

            `OPCODE_ANDREG: begin
                Reg2Loc = 1'b0;
                ALUSrc = 1'b0;
                MemtoReg = 1'b0;
                RegWrite = 1'b1;
                MemRead = 1'b0;
                MemWrite = 1'b0;
                Branch = 1'b0;
                Uncondbranch = 1'b0;
                ALUOp = 4'b0000;  // AND
                SignOp = 2'b00;
            end

            `OPCODE_ORRREG: begin
                Reg2Loc = 1'b0;
                ALUSrc = 1'b0;
                MemtoReg = 1'b0;
                RegWrite = 1'b1;
                MemRead = 1'b0;
                MemWrite = 1'b0;
                Branch = 1'b0;
                Uncondbranch = 1'b0;
                ALUOp = 4'b0001;  // ORR
                SignOp = 2'b00;
            end

            // I-format instructions (immediate operations)
            `OPCODE_ADDIMM: begin
                Reg2Loc = 1'b0;
                ALUSrc = 1'b1;
                MemtoReg = 1'b0;
                RegWrite = 1'b1;
                MemRead = 1'b0;
                MemWrite = 1'b0;
                Branch = 1'b0;
                Uncondbranch = 1'b0;
                ALUOp = 4'b0010;  // ADD
                SignOp = 2'b00;   // Zero extend for immediate
            end

            `OPCODE_SUBIMM: begin
                Reg2Loc = 1'b0;
                ALUSrc = 1'b1;
                MemtoReg = 1'b0;
                RegWrite = 1'b1;
                MemRead = 1'b0;
                MemWrite = 1'b0;
                Branch = 1'b0;
                Uncondbranch = 1'b0;
                ALUOp = 4'b0110;  // SUB
                SignOp = 2'b00;   // Zero extend for immediate
            end

            // D-format instructions (load/store)
            `OPCODE_LDUR: begin
                Reg2Loc = 1'b0;
                ALUSrc = 1'b1;
                MemtoReg = 1'b1;
                RegWrite = 1'b1;
                MemRead = 1'b1;
                MemWrite = 1'b0;
                Branch = 1'b0;
                Uncondbranch = 1'b0;
                ALUOp = 4'b0010;  // ADD for address calculation
                SignOp = 2'b01;   // Sign extend for D-format offset
            end

            `OPCODE_STUR: begin
                Reg2Loc = 1'b1;   // Select Rm for write data
                ALUSrc = 1'b1;
                MemtoReg = 1'b0;  // Don't care
                RegWrite = 1'b0;
                MemRead = 1'b0;
                MemWrite = 1'b1;
                Branch = 1'b0;
                Uncondbranch = 1'b0;
                ALUOp = 4'b0010;  // ADD for address calculation
                SignOp = 2'b01;   // Sign extend for D-format offset
            end

            // CB-format instructions (conditional branch)
            `OPCODE_CBZ: begin
                Reg2Loc = 1'b1;   // Select Rt for comparison
                ALUSrc = 1'b0;
                MemtoReg = 1'b0;  // Don't care
                RegWrite = 1'b0;
                MemRead = 1'b0;
                MemWrite = 1'b0;
                Branch = 1'b1;
                Uncondbranch = 1'b0;
                ALUOp = 4'b0111;  // Pass through for zero check
                SignOp = 2'b10;   // Sign extend for CB-format offset
            end

            // B-format instructions (unconditional branch)
            `OPCODE_B: begin
                Reg2Loc = 1'b0;   // Don't care
                ALUSrc = 1'b0;    // Don't care
                MemtoReg = 1'b0;  // Don't care
                RegWrite = 1'b0;
                MemRead = 1'b0;
                MemWrite = 1'b0;
                Branch = 1'b0;    // Not used for unconditional
                Uncondbranch = 1'b1;
                ALUOp = 4'b0000;  // Don't care
                SignOp = 2'b11;   // Sign extend for B-format offset
            end

            // MOVZ instruction
            `OPCODE_MOVZ: begin
                Reg2Loc = 1'b0;
                ALUSrc = 1'b1;
                MemtoReg = 1'b0;
                RegWrite = 1'b1;
                MemRead = 1'b0;
                MemWrite = 1'b0;
                Branch = 1'b0;
                Uncondbranch = 1'b0;
                ALUOp = 4'b0111;  // Pass through B input
                SignOp = 2'b00;   // Zero extend and shift for MOVZ
            end

            // Default case: undefined opcode, all outputs remain 0
            default: begin
                Reg2Loc = 1'b0;
                ALUSrc = 1'b0;
                MemtoReg = 1'b0;
                RegWrite = 1'b0;
                MemRead = 1'b0;
                MemWrite = 1'b0;
                Branch = 1'b0;
                Uncondbranch = 1'b0;
                ALUOp = 4'b0000;
                SignOp = 2'b00;
            end
        endcase
    end

endmodule

InstructionMemory.v
`timescale 1ns / 1ps
/*
 * Module: InstructionMemory
 *
 * Implements read-only instruction memory
 * 
 */
module InstructionMemory(Data, Address);
   parameter T_rd = 20;
   parameter MemSize = 40;
   
   output [31:0] Data;
   input [63:0]  Address;
   reg [31:0] 	 Data;
   
   /*
    * ECEN 350 Processor Test Functions
    * Texas A&M University
    */
   
   always @ (Address) begin

      case(Address)

	/* Test Program 1:
	 * Program loads constants from the data memory. Uses these constants to test
	 * the following instructions: LDUR, ORR, AND, CBZ, ADD, SUB, STUR and B.
	 * 
	 * Assembly code for test:
	 * 
	 * 0: LDUR X9, [XZR, 0x0]    //Load 1 into x9
	 * 4: LDUR X10, [XZR, 0x8]   //Load a into x10
	 * 8: LDUR X11, [XZR, 0x10]  //Load 5 into x11
	 * C: LDUR X12, [XZR, 0x18]  //Load big constant into x12
	 * 10: LDUR X13, [XZR, 0x20]  //load a 0 into X13
	 * 
	 * 14: ORR X10, X10, X11  //Create mask of 0xf
	 * 18: AND X12, X12, X10  //Mask off low order bits of big constant
	 * 
	 * loop:
	 * 1C: CBZ X12, end  //while X12 is not 0
	 * 20: ADD X13, X13, X9  //Increment counter in X13
	 * 24: SUB X12, X12, X9  //Decrement remainder of big constant in X12
	 * 28: B loop  //Repeat till X12 is 0
	 * 2C: STUR X13, [XZR, 0x20]  //store back the counter value into the memory location 0x20
	 */
	

	63'h000: Data = 32'hF84003E9;
	63'h004: Data = 32'hF84083EA;
	63'h008: Data = 32'hF84103EB;
	63'h00c: Data = 32'hF84183EC;
	63'h010: Data = 32'hF84203ED;
	63'h014: Data = 32'hAA0B014A;
	63'h018: Data = 32'h8A0A018C;
	63'h01c: Data = 32'hB400008C;
	63'h020: Data = 32'h8B0901AD;
	63'h024: Data = 32'hCB09018C;
	63'h028: Data = 32'h17FFFFFD;
	63'h02c: Data = 32'hF80203ED;
	63'h030: Data = 32'hF84203ED;  //One last load to place stored value on memdbus for test checking.

	/* Add code for your tests here */

	
	default: Data = 32'hXXXXXXXX;
      endcase
   end
endmodule



// https://chatgpt.com/g/g-p-68fa84289bfc81918d42fdf621b4ce84-will/c/69027ea8-2ad8-8321-9d68-4308f0d9044f

SingleCycleProc.v
module SingleCycleProc(
		   input	     reset, //Active High
		   input [63:0]	     startpc,
		   output reg [63:0] currentpc,
		   output [63:0]     MemtoRegOut, // this should be
						   // attached to the
						   // output of the
						   // MemtoReg Mux
		   input	     CLK
		   );

   // Next PC connections
   wire [63:0] 			     nextpc;       // The next PC, to be updated on clock cycle

   // Instruction Memory connections
   wire [31:0] 			     instruction;  // The current instruction

   // Parts of instruction
   wire [4:0] 			     rd;            // The destination register
   wire [4:0] 			     rm;            // Operand 1
   wire [4:0] 			     rn;            // Operand 2
   wire [10:0] 			     opcode;

   // Control wires
   wire 			     Reg2Loc;
   wire 			     ALUSrc;
   wire 			     MemtoReg;
   wire 			     RegWrite;
   wire 			     MemRead;
   wire 			     MemWrite;
   wire 			     Branch;
   wire 			     Uncondbranch;
   wire [3:0] 			     ALUop;
   wire [1:0] 			     SignOp;

   // Register file connections
   wire [63:0] 			     regoutA;     // Output A
   wire [63:0] 			     regoutB;     // Output B

   // ALU connections
   wire [63:0] 			     aluout;
   wire 			     zero;

   // Sign Extender connections
   wire [63:0] 			     extimm;

   // Data Memory connections
   wire [63:0] 			     readdata;

   // Mux outputs
   wire [63:0] 			     aluinputB;   // Output of ALUSrc mux

   // PC update logic
   always @(posedge CLK)
     begin
        if (reset)
          currentpc <= #3 startpc;
        else
          currentpc <= #3 nextpc;
     end

   // Parts of instruction
   assign rd = instruction[4:0];
   assign rn = instruction[9:5];
   assign rm = Reg2Loc ? instruction[4:0] : instruction[20:16];
   assign opcode = instruction[31:21];

   // Instruction Memory
   InstructionMemory imem(
			  .Data(instruction),
			  .Address(currentpc)
			  );

   // Control Unit
   SC_Control SingleCycleControl(
		   .Reg2Loc(Reg2Loc),
		   .ALUSrc(ALUSrc),
		   .MemtoReg(MemtoReg),
		   .RegWrite(RegWrite),
		   .MemRead(MemRead),
		   .MemWrite(MemWrite),
		   .Branch(Branch),
		   .Uncondbranch(Uncondbranch),
		   .ALUOp(ALUop),
		   .SignOp(SignOp),
		   .opcode(opcode)
		   );

   /*
    * Connect the remaining datapath elements below.
    * Do not forget any additional multiplexers that may be required.
    */

   // Register File
   RegisterFile rf(
		   .BusA(regoutA),
		   .BusB(regoutB),
		   .BusW(MemtoRegOut),
		   .RA(rn),
		   .RB(rm),
		   .RW(rd),
		   .RegWr(RegWrite),
		   .Clk(CLK)
		   );

   // Sign Extender
   SignExtender se(
		   .SignExOut(extimm),
		   .Instruction(instruction[25:0]),
		   .SignOp(SignOp)
		   );

   // ALUSrc Mux (selects between register B and immediate)
   assign aluinputB = ALUSrc ? extimm : regoutB;

   // ALU
   ALU alu(
	   .BusW(aluout),
	   .BusA(regoutA),
	   .BusB(aluinputB),
	   .ALUCtrl(ALUop),
	   .Zero(zero)
	   );

   // Data Memory
   DataMemory dmem(
		   .ReadData(readdata),
		   .Address(aluout),
		   .WriteData(regoutB),
		   .MemoryRead(MemRead),
		   .MemoryWrite(MemWrite),
		   .Clock(CLK)
		   );

   // MemtoReg Mux (selects between ALU output and memory read data)
   assign MemtoRegOut = MemtoReg ? readdata : aluout;

   // Next PC Logic
   NextPClogic nextpclogic(
			   .NextPC(nextpc),
			   .CurrentPC(currentpc),
			   .SignExtImm64(extimm),
			   .Branch(Branch),
			   .ALUZero(zero),
			   .Uncondbranch(Uncondbranch)
			   );

endmodule

// https://chatgpt.com/g/g-p-68fa84289bfc81918d42fdf621b4ce84-will/c/69028982-6c24-8331-8064-0ea752a9b04d

SingleCycleProcTest.v
`timescale 1ns / 1ps

`define STRLEN 32
`define HalfClockPeriod 60
`define ClockPeriod `HalfClockPeriod * 2

module SingleCycleProcTest_v;

   initial
     begin
        $dumpfile("singlecycle.vcd");
        $dumpvars;
     end

   task passTest;
      input [63:0] actualOut, expectedOut;
      input [`STRLEN*8:0] testType;
      inout [7:0] 	  passed;

      if(actualOut == expectedOut) begin $display ("%s passed", testType); passed = passed + 1; end
      else $display ("%s failed: 0x%x should be 0x%x", testType, actualOut, expectedOut);
   endtask

   task allPassed;
      input [7:0] passed;
      input [7:0] numTests;

      if(passed == numTests) $display ("All tests passed");
      else $display("Some tests failed: %d of %d passed", passed, numTests);
   endtask

   // Inputs
   reg 		  CLK;
   reg		  Reset;
   reg [63:0] 	  startPC;
   reg [7:0] 	  passed;
   reg [15:0] 	  watchdog;

   // Outputs
   wire [63:0] 	  MemtoRegOut;
   wire [63:0] 	  currentPC;

   // Instantiate the Unit Under Test (UUT)
   SingleCycleProc uut (
		    .CLK(CLK),
		    .reset(Reset),
		    .startpc(startPC),
		    .currentpc(currentPC),
		    .MemtoRegOut(MemtoRegOut)
		    );

   initial begin
      // Initialize Inputs
      Reset = 0;
      startPC = 0;
      passed = 0;

      // Initialize Watchdog timer
      watchdog = 0;

      // Wait for global reset
      #(1 * `ClockPeriod);

      // Program 1
      #1
        Reset = 1; startPC = 0;
      @(posedge CLK);
      @(negedge CLK);
      @(posedge CLK);
      Reset = 0;

      $display("PC     Rd Rn Rm  X9               X10              X11              X12              X13              RW BusW             ALU              Inst");
      while (currentPC < 64'h30)
        begin
	   @(posedge CLK);
	   @(negedge CLK);
           $display("%h %d  %d  %d   %h %h %h %h %h %b  %h %h %h", 
                    currentPC,
                    uut.rd,
                    uut.rn,
                    uut.rm,
                    uut.rf.rf[9], 
                    uut.rf.rf[10], 
                    uut.rf.rf[11], 
                    uut.rf.rf[12], 
                    uut.rf.rf[13], 
                    uut.RegWrite,
                    uut.MemtoRegOut,
                    uut.aluout,
                    uut.instruction);
        end
      passTest(MemtoRegOut, 64'hF, "Results of Program 1", passed);

      allPassed(passed, 1);
      $finish;
   end

   // Initialize the clock to be 0
   initial begin
      CLK = 0;
   end

   // The following is correct if clock starts at LOW level at StartTime //
   always begin
      #`HalfClockPeriod CLK = ~CLK;
      #`HalfClockPeriod CLK = ~CLK;
      watchdog = watchdog +1;
   end

   // Kill the simulation if the watchdog hits 32 cycles to prevent excessive output
   always @*
     if (watchdog == 16'h20)
       begin
          $display("Watchdog Timer Expired - stopping at 32 cycles");
          $finish;
       end

endmodule

singlecycle.vcd
$date
	Wed Oct 29 18:57:10 2025
$end
$version
	Icarus Verilog
$end
$timescale
	1ps
$end
$scope module SingleCycleProcTest_v $end
$var wire 64 ! currentPC [63:0] $end
$var wire 64 " MemtoRegOut [63:0] $end
$var reg 1 # CLK $end
$var reg 1 $ Reset $end
$var reg 8 % passed [7:0] $end
$var reg 64 & startPC [63:0] $end
$var reg 16 ' watchdog [15:0] $end
$scope module uut $end
$var wire 1 # CLK $end
$var wire 1 $ reset $end
$var wire 64 ( startpc [63:0] $end
$var wire 1 ) zero $end
$var wire 5 * rn [4:0] $end
$var wire 5 + rm [4:0] $end
$var wire 64 , regoutB [63:0] $end
$var wire 64 - regoutA [63:0] $end
$var wire 64 . readdata [63:0] $end
$var wire 5 / rd [4:0] $end
$var wire 11 0 opcode [10:0] $end
$var wire 64 1 nextpc [63:0] $end
$var wire 32 2 instruction [31:0] $end
$var wire 64 3 extimm [63:0] $end
$var wire 64 4 aluout [63:0] $end
$var wire 64 5 aluinputB [63:0] $end
$var wire 1 6 Uncondbranch $end
$var wire 2 7 SignOp [1:0] $end
$var wire 1 8 RegWrite $end
$var wire 1 9 Reg2Loc $end
$var wire 64 : MemtoRegOut [63:0] $end
$var wire 1 ; MemtoReg $end
$var wire 1 < MemWrite $end
$var wire 1 = MemRead $end
$var wire 1 > Branch $end
$var wire 4 ? ALUop [3:0] $end
$var wire 1 @ ALUSrc $end
$var reg 64 A currentpc [63:0] $end
$scope module SingleCycleControl $end
$var wire 11 B opcode [10:0] $end
$var reg 4 C ALUOp [3:0] $end
$var reg 1 @ ALUSrc $end
$var reg 1 > Branch $end
$var reg 1 = MemRead $end
$var reg 1 < MemWrite $end
$var reg 1 ; MemtoReg $end
$var reg 1 9 Reg2Loc $end
$var reg 1 8 RegWrite $end
$var reg 2 D SignOp [1:0] $end
$var reg 1 6 Uncondbranch $end
$upscope $end
$scope module alu $end
$var wire 4 E ALUCtrl [3:0] $end
$var wire 64 F BusB [63:0] $end
$var wire 1 ) Zero $end
$var wire 64 G BusA [63:0] $end
$var reg 64 H BusW [63:0] $end
$upscope $end
$scope module dmem $end
$var wire 64 I Address [63:0] $end
$var wire 1 # Clock $end
$var wire 1 = MemoryRead $end
$var wire 1 < MemoryWrite $end
$var wire 64 J WriteData [63:0] $end
$var reg 64 K ReadData [63:0] $end
$scope task initset $end
$var reg 64 L addr [63:0] $end
$var reg 64 M data [63:0] $end
$upscope $end
$upscope $end
$scope module imem $end
$var wire 64 N Address [63:0] $end
$var parameter 32 O MemSize $end
$var parameter 32 P T_rd $end
$var reg 32 Q Data [31:0] $end
$upscope $end
$scope module nextpclogic $end
$var wire 1 ) ALUZero $end
$var wire 1 > Branch $end
$var wire 64 R CurrentPC [63:0] $end
$var wire 1 6 Uncondbranch $end
$var wire 64 S SignExtImm64 [63:0] $end
$var reg 64 T NextPC [63:0] $end
$upscope $end
$scope module rf $end
$var wire 64 U BusA [63:0] $end
$var wire 64 V BusB [63:0] $end
$var wire 64 W BusW [63:0] $end
$var wire 1 # Clk $end
$var wire 5 X RA [4:0] $end
$var wire 5 Y RB [4:0] $end
$var wire 5 Z RW [4:0] $end
$var wire 1 8 RegWr $end
$var reg 64 [ a_next [63:0] $end
$var reg 64 \ b_next [63:0] $end
$upscope $end
$scope module se $end
$var wire 26 ] Instruction [25:0] $end
$var wire 2 ^ SignOp [1:0] $end
$var reg 64 _ SignExOut [63:0] $end
$upscope $end
$upscope $end
$scope task allPassed $end
$var reg 8 ` numTests [7:0] $end
$var reg 8 a passed [7:0] $end
$upscope $end
$scope task passTest $end
$var reg 64 b actualOut [63:0] $end
$var reg 64 c expectedOut [63:0] $end
$var reg 8 d passed [7:0] $end
$var reg 257 e testType [256:0] $end
$upscope $end
$upscope $end
$enddefinitions $end
$comment Show the parameter values. $end
$dumpall
b10100 P
b101000 O
$end
#0
$dumpvars
bx e
bx d
bx c
bx b
bx a
bx `
bx _
bx ^
bx ]
bx \
bx [
bx Z
bx Y
bx X
bx W
bx V
bx U
bx T
bx S
bx R
bx Q
bx N
b0 M
b100000 L
bx K
bx J
bx I
bx H
bx G
bx F
bx E
bx D
bx C
bx B
bx A
x@
bx ?
x>
x=
x<
x;
bx :
x9
x8
bx 7
x6
bx 5
bx 4
bx 3
bx 2
bx 1
bx 0
bx /
bx .
bx -
bx ,
bx +
bx *
x)
b0 (
b0 '
b0 &
b0 %
0$
0#
bx "
bx !
$end
#60000
1#
#120000
b1 '
0#
#121000
1$
#180000
1#
#183000
b0 5
b0 F
b0 3
b0 S
b0 _
b1 7
b1 D
b1 ^
b10 ?
b10 C
b10 E
06
0>
0<
1=
18
1;
1@
09
b0 +
b0 Y
b0 [
b10000000000001111101001 ]
b11111000010 0
b11111000010 B
b11111 *
b11111 X
b1001 /
b1001 Z
b11111000010000000000001111101001 2
b11111000010000000000001111101001 Q
b100 1
b100 T
b0 !
b0 A
b0 N
b0 R
#186000
b1 "
b1 :
b1 W
b1 .
b1 K
1)
b0 4
b0 H
b0 I
b0 -
b0 G
b0 U
#240000
b10 '
0#
#300000
0$
1#
#303000
b1010 "
b1010 :
b1010 W
b1010 .
b1010 K
0)
b1000 4
b1000 H
b1000 I
b1000 5
b1000 F
b1000 3
b1000 S
b1000 _
b10000001000001111101010 ]
b1010 /
b1010 Z
b11111000010000001000001111101010 2
b11111000010000001000001111101010 Q
b1000 1
b1000 T
b100 !
b100 A
b100 N
b100 R
#360000
b11 '
0#
#420000
1#
#423000
b101 "
b101 :
b101 W
b101 .
b101 K
b10000 4
b10000 H
b10000 I
b10000 5
b10000 F
b10000 3
b10000 S
b10000 _
b1 +
b1 Y
b10000010000001111101011 ]
b1011 /
b1011 Z
b11111000010000010000001111101011 2
b11111000010000010000001111101011 Q
b1100 1
b1100 T
b1000 !
b1000 A
b1000 N
b1000 R
#480000
b100 '
0#
#540000
1#
#543000
b111111111011111010100111110111101010110110111110111011111111 "
b111111111011111010100111110111101010110110111110111011111111 :
b111111111011111010100111110111101010110110111110111011111111 W
b111111111011111010100111110111101010110110111110111011111111 .
b111111111011111010100111110111101010110110111110111011111111 K
b11000 4
b11000 H
b11000 I
b11000 5
b11000 F
b11000 3
b11000 S
b11000 _
b10000011000001111101100 ]
b1100 /
b1100 Z
b11111000010000011000001111101100 2
b11111000010000011000001111101100 Q
b10000 1
b10000 T
b1100 !
b1100 A
b1100 N
b1100 R
#600000
b101 '
0#
#660000
1#
#663000
b0 "
b0 :
b0 W
b0 .
b0 K
b100000 4
b100000 H
b100000 I
b100000 5
b100000 F
b100000 3
b100000 S
b100000 _
b10 +
b10 Y
b10000100000001111101101 ]
b1101 /
b1101 Z
b11111000010000100000001111101101 2
b11111000010000100000001111101101 Q
b10100 1
b10100 T
b10000 !
b10000 A
b10000 N
b10000 R
#720000
b110 '
0#
#780000
1#
#783000
x)
bx 4
bx H
bx I
bx .
bx K
bx "
bx :
bx W
bx 5
bx F
b101 \
b1011000000 3
b1011000000 S
b1011000000 _
b0 7
b0 D
b0 ^
b1 ?
b1 C
b1 E
0=
18
0;
0@
b1011 +
b1011 Y
bx [
b10000010110000000101001010 ]
b10101010000 0
b10101010000 B
b1010 *
b1010 X
b1010 /
b1010 Z
b10101010000010110000000101001010 2
b10101010000010110000000101001010 Q
b11000 1
b11000 T
b10100 !
b10100 A
b10100 N
b10100 R
#786000
bx1x1 [
bx1x1 "
bx1x1 :
bx1x1 W
0)
bx1x1 4
bx1x1 H
bx1x1 I
b101 5
b101 F
b101 ,
b101 J
b101 V
bx -
bx G
bx U
#789000
bx1x1 -
bx1x1 G
bx1x1 U
#840000
b111 '
0#
#900000
1#
#903000
b101 "
b101 :
b101 W
b101 4
b101 H
b101 I
bx1x1 \
b1010000000 3
b1010000000 S
b1010000000 _
b0 ?
b0 C
b0 E
18
b1010 +
b1010 Y
b101 [
b10000010100000000110001100 ]
b10001010000 0
b10001010000 B
b1100 *
b1100 X
b1100 /
b1100 Z
b10001010000010100000000110001100 2
b10001010000010100000000110001100 Q
b11100 1
b11100 T
b11000 !
b11000 A
b11000 N
b11000 R
#906000
bx1x1 5
bx1x1 F
bx1x1 ,
bx1x1 J
bx1x1 V
b101 -
b101 G
b101 U
#960000
b1000 '
0#
#1020000
1#
#1023000
bx1x1 "
bx1x1 :
bx1x1 W
bx1x1 4
bx1x1 H
bx1x1 I
b101 \
b10000 3
b10000 S
b10000 _
b10 7
b10 D
b10 ^
b111 ?
b111 C
b111 E
1>
19
08
b1100 +
b1100 Y
bx [
b10001100 ]
b10110100000 0
b10110100000 B
b100 *
b100 X
b10110100000000000000000010001100 2
b10110100000000000000000010001100 Q
b100000 1
b100000 T
b11100 !
b11100 A
b11100 N
b11100 R
#1026000
b101 "
b101 :
b101 W
b101 4
b101 H
b101 I
b101 5
b101 F
b101 ,
b101 J
b101 V
bx -
bx G
bx U
#1080000
b1001 '
0#
#1140000
1#
#1143000
bx "
bx :
bx W
x)
bx 4
bx H
bx I
b1 \
b1001000000 3
b1001000000 S
b1001000000 _
18
b0 7
b0 D
b0 ^
b10 ?
b10 C
b10 E
0>
09
b1001 +
b1001 Y
bx [
b11000010010000000110101101 ]
b10001011000 0
b10001011000 B
b1101 *
b1101 X
b1101 /
b1101 Z
b10001011000010010000000110101101 2
b10001011000010010000000110101101 Q
b100100 1
b100100 T
b100000 !
b100000 A
b100000 N
b100000 R
#1146000
b1 5
b1 F
b1 ,
b1 J
b1 V
#1200000
b1010 '
0#
#1260000
1#
